sipper/__init__.py
sipper/__main__.py
sipper/getopt.py
sipper/driver/__init__.py
sipper/driver/avs84.py
sipper/driver/csv.py
sipper/driver/excel.py
sipper-0.0.6.dist-info/LICENSE
sipper-0.0.6.dist-info/METADATA
sipper-0.0.6.dist-info/WHEEL
sipper-0.0.6.dist-info/top_level.txt
sipper-0.0.6.dist-info/RECORD
