Metadata-Version: 2.1
Name: sipper
Version: 0.0.6
Summary: The FFMPEG for proprietary data file formats
Home-page: https://github.com/mxi/sipper
Author: Maxim Kasyanenko
License: UNKNOWN
Project-URL: Bug Tracker, https://github.com/mxi/sipper/issues
Platform: UNKNOWN
Classifier: Development Status :: 1 - Planning
Classifier: Programming Language :: Python :: 3
Classifier: License :: OSI Approved :: GNU General Public License v3 (GPLv3)
Requires-Python: >=3.6
License-File: LICENSE
Requires-Dist: pandas (>=1.2.0)
Requires-Dist: xlrd (>=1.0.0)
Requires-Dist: openpyxl (>=3.0.0)
